sift_dev_logger/__init__.py
sift_dev_logger/common.py
sift_dev_logger/config.py
sift_dev_logger/fastapi.py
sift_dev_logger/flask.py
sift_dev_logger/handlers.py
sift_dev_logger-2.0.1.dist-info/METADATA
sift_dev_logger-2.0.1.dist-info/WHEEL
sift_dev_logger-2.0.1.dist-info/RECORD
