Metadata-Version: 2.4
Name: sift-dev-logger
Version: 2.0.1
Summary: A logging SDK for Sift Dev that supports Flask and FastAPI
Project-URL: Homepage, https://github.com/sift-dev/python-sdk/
Project-URL: Documentation, https://github.com/sift-dev/python-sdk/tree/main/sift_dev_logger/README.md
Project-URL: Repository, https://github.com/sift-dev/python-sdk.git
Author-email: Sift Dev <support@runsift.com>
License-Expression: MIT
Keywords: dev,django,fastapi,flask,logging,sift
Classifier: Development Status :: 3 - Alpha
Classifier: Intended Audience :: Developers
Classifier: License :: OSI Approved :: MIT License
Classifier: Programming Language :: Python :: 3
Classifier: Programming Language :: Python :: 3.8
Classifier: Programming Language :: Python :: 3.9
Classifier: Programming Language :: Python :: 3.10
Classifier: Programming Language :: Python :: 3.11
Requires-Dist: requests>=2.25.0
Provides-Extra: all
Requires-Dist: fastapi>=0.68.0; extra == 'all'
Requires-Dist: flask>=2.0.0; extra == 'all'
Requires-Dist: httpx>=0.24.0; extra == 'all'
Provides-Extra: dev
Requires-Dist: build>=0.10.0; extra == 'dev'
Requires-Dist: flake8>=3.8.0; extra == 'dev'
Requires-Dist: httpx>=0.24.0; extra == 'dev'
Requires-Dist: pytest>=6.0.0; extra == 'dev'
Requires-Dist: twine>=4.0.0; extra == 'dev'
Provides-Extra: fastapi
Requires-Dist: fastapi>=0.68.0; extra == 'fastapi'
Requires-Dist: httpx>=0.24.0; extra == 'fastapi'
Provides-Extra: flask
Requires-Dist: flask>=2.0.0; extra == 'flask'
